datefmt/__init__.py
datefmt/py.typed
datefmt-0.0.1.1.dist-info/METADATA
datefmt-0.0.1.1.dist-info/WHEEL
datefmt-0.0.1.1.dist-info/licenses/LICENSE
datefmt-0.0.1.1.dist-info/RECORD
